<?xml version="1.0" encoding="UTF-8"?>
<retrailRecorder>
<record ms="13">
<methodCall xmlns:ex="http://ws.apache.org/xmlrpc/namespaces/extensions"><methodName>UConS.heartbeat</methodName><params><param><value>https://localhost:8091</value></param><param><value><array><data/></array></value></param></params></methodCall>
<methodResponse xmlns:ex="http://ws.apache.org/xmlrpc/namespaces/extensions"><params><param><value><ex:dom><Heartbeat><Responses/><Config watchdogPeriod="15" version="2" maxMissedHeartbeats="1"/></Heartbeat></ex:dom></value></param></params></methodResponse>
</record>
<record ms="115">
<methodCall xmlns:ex="http://ws.apache.org/xmlrpc/namespaces/extensions"><methodName>UConS.echo</methodName><params><param><value><ex:dom><echoTest/></ex:dom></value></param></params></methodCall>
<methodResponse xmlns:ex="http://ws.apache.org/xmlrpc/namespaces/extensions"><params><param><value><ex:dom><echoTest/></ex:dom></value></param></params></methodResponse>
</record>
<record ms="139">
<methodCall xmlns:ex="http://ws.apache.org/xmlrpc/namespaces/extensions"><methodName>UConS.tryAccess</methodName><params><param><value><ex:dom><Request xmlns="urn:oasis:names:tc:xacml:3.0:core:schema:wd-17" ReturnPolicyIdList="false" CombinedDecision="false"><Attributes Category="urn:oasis:names:tc:xacml:3.0:attribute-category:resource"><Attribute Issuer="issuer" IncludeInResult="false" AttributeId="urn:oasis:names:tc:xacml:1.0:resource:resource-id"><AttributeValue DataType="http://www.w3.org/2001/XMLSchema#string"/></Attribute></Attributes><Attributes Category="urn:oasis:names:tc:xacml:1.0:subject-category:access-subject"><Attribute Issuer="issuer" IncludeInResult="false" AttributeId="urn:oasis:names:tc:xacml:1.0:subject:subject-id"><AttributeValue DataType="http://www.w3.org/2001/XMLSchema#string">fedoraRole</AttributeValue></Attribute></Attributes><Attributes Category="urn:oasis:names:tc:xacml:3.0:attribute-category:action"><Attribute Issuer="issuer" IncludeInResult="false" AttributeId="urn:oasis:names:tc:xacml:1.0:action:action-id"><AttributeValue DataType="http://www.w3.org/2001/XMLSchema#string">urn:fedora:names:fedora:2.1:action:id-getDatastreamDissemination</AttributeValue></Attribute></Attributes></Request></ex:dom></value></param><param><value>https://localhost:8091</value></param><param><value><ex:nil/></value></param></params></methodCall>
<methodResponse xmlns:ex="http://ws.apache.org/xmlrpc/namespaces/extensions"><params><param><value><ex:dom><Response xmlns="urn:oasis:names:tc:xacml:3.0:core:schema:wd-17"><Result><Decision>Permit</Decision><StatusMessage/></Result><Session uuid="7BE74989-1229-4FAF-9F55-919D813F2225" uconUrl="https://localhost:8090" stateType="PASSIVE" stateName="TRY" ms="136"/></Response></ex:dom></value></param></params></methodResponse>
</record>
<record ms="317">
<methodCall xmlns:ex="http://ws.apache.org/xmlrpc/namespaces/extensions"><methodName>UConS.endAccess</methodName><params><param><value>7BE74989-1229-4FAF-9F55-919D813F2225</value></param><param><value></value></param></params></methodCall>
<methodResponse xmlns:ex="http://ws.apache.org/xmlrpc/namespaces/extensions"><params><param><value><ex:dom><Response xmlns="urn:oasis:names:tc:xacml:3.0:core:schema:wd-17"><Result><Decision>Permit</Decision><StatusMessage/></Result><Session uuid="7BE74989-1229-4FAF-9F55-919D813F2225" uconUrl="https://localhost:8090" stateType="END" stateName="DELETED" ms="302"/></Response></ex:dom></value></param></params></methodResponse>
</record>
<record ms="650">
<methodCall xmlns:ex="http://ws.apache.org/xmlrpc/namespaces/extensions"><methodName>UConS.tryAccess</methodName><params><param><value><ex:dom><Request xmlns="urn:oasis:names:tc:xacml:3.0:core:schema:wd-17" ReturnPolicyIdList="false" CombinedDecision="false"><Attributes Category="urn:oasis:names:tc:xacml:3.0:attribute-category:resource"><Attribute Issuer="issuer" IncludeInResult="false" AttributeId="urn:oasis:names:tc:xacml:1.0:resource:resource-id"><AttributeValue DataType="http://www.w3.org/2001/XMLSchema#string"/></Attribute></Attributes><Attributes Category="urn:oasis:names:tc:xacml:1.0:subject-category:access-subject"><Attribute Issuer="issuer" IncludeInResult="false" AttributeId="urn:oasis:names:tc:xacml:1.0:subject:subject-id"><AttributeValue DataType="http://www.w3.org/2001/XMLSchema#string">fedoraRole</AttributeValue></Attribute></Attributes><Attributes Category="urn:oasis:names:tc:xacml:3.0:attribute-category:action"><Attribute Issuer="issuer" IncludeInResult="false" AttributeId="urn:oasis:names:tc:xacml:1.0:action:action-id"><AttributeValue DataType="http://www.w3.org/2001/XMLSchema#string">urn:fedora:names:fedora:2.1:action:id-getDatastreamDissemination</AttributeValue></Attribute></Attributes></Request></ex:dom></value></param><param><value>https://localhost:8091</value></param><param><value>ziopino</value></param></params></methodCall>
<methodResponse xmlns:ex="http://ws.apache.org/xmlrpc/namespaces/extensions"><params><param><value><ex:dom><Response xmlns="urn:oasis:names:tc:xacml:3.0:core:schema:wd-17"><Result><Decision>Permit</Decision><StatusMessage/></Result><Session uuid="CD85F23C-D39C-4ABA-9F24-32348DF253A5" uconUrl="https://localhost:8090" stateType="PASSIVE" stateName="TRY" ms="122" customId="ziopino"/></Response></ex:dom></value></param></params></methodResponse>
</record>
<record ms="808">
<methodCall xmlns:ex="http://ws.apache.org/xmlrpc/namespaces/extensions"><methodName>UConS.endAccess</methodName><params><param><value><ex:nil/></value></param><param><value>ziopino</value></param></params></methodCall>
<methodResponse xmlns:ex="http://ws.apache.org/xmlrpc/namespaces/extensions"><params><param><value><ex:dom><Response xmlns="urn:oasis:names:tc:xacml:3.0:core:schema:wd-17"><Result><Decision>Permit</Decision><StatusMessage/></Result><Session uuid="CD85F23C-D39C-4ABA-9F24-32348DF253A5" uconUrl="https://localhost:8090" stateType="END" stateName="DELETED" ms="314" customId="ziopino"/></Response></ex:dom></value></param></params></methodResponse>
</record>
<record ms="1158">
<methodCall xmlns:ex="http://ws.apache.org/xmlrpc/namespaces/extensions"><methodName>UConS.tryAccess</methodName><params><param><value><ex:dom><Request xmlns="urn:oasis:names:tc:xacml:3.0:core:schema:wd-17" ReturnPolicyIdList="false" CombinedDecision="false"><Attributes Category="urn:oasis:names:tc:xacml:3.0:attribute-category:resource"><Attribute Issuer="issuer" IncludeInResult="false" AttributeId="urn:oasis:names:tc:xacml:1.0:resource:resource-id"><AttributeValue DataType="http://www.w3.org/2001/XMLSchema#string"/></Attribute></Attributes><Attributes Category="urn:oasis:names:tc:xacml:1.0:subject-category:access-subject"><Attribute Issuer="issuer" IncludeInResult="false" AttributeId="urn:oasis:names:tc:xacml:1.0:subject:subject-id"><AttributeValue DataType="http://www.w3.org/2001/XMLSchema#string">fedoraRole</AttributeValue></Attribute></Attributes><Attributes Category="urn:oasis:names:tc:xacml:3.0:attribute-category:action"><Attribute Issuer="issuer" IncludeInResult="false" AttributeId="urn:oasis:names:tc:xacml:1.0:action:action-id"><AttributeValue DataType="http://www.w3.org/2001/XMLSchema#string">urn:fedora:names:fedora:2.1:action:id-getDatastreamDissemination</AttributeValue></Attribute></Attributes></Request></ex:dom></value></param><param><value>https://localhost:8091</value></param><param><value>ziopino2</value></param></params></methodCall>
<methodResponse xmlns:ex="http://ws.apache.org/xmlrpc/namespaces/extensions"><params><param><value><ex:dom><Response xmlns="urn:oasis:names:tc:xacml:3.0:core:schema:wd-17"><Result><Decision>Permit</Decision><StatusMessage/></Result><Session uuid="68FDC91F-3146-436C-BE1D-0C7378A819EF" uconUrl="https://localhost:8090" stateType="PASSIVE" stateName="TRY" ms="170" customId="ziopino2"/></Response></ex:dom></value></param></params></methodResponse>
</record>
<record ms="1372">
<methodCall xmlns:ex="http://ws.apache.org/xmlrpc/namespaces/extensions"><methodName>UConS.assignCustomId</methodName><params><param><value><ex:nil/></value></param><param><value>ziopino2</value></param><param><value>ziopino</value></param></params></methodCall>
<methodResponse xmlns:ex="http://ws.apache.org/xmlrpc/namespaces/extensions"><params><param><value><ex:dom><Response xmlns="urn:oasis:names:tc:xacml:3.0:core:schema:wd-17"><Result><Decision>Permit</Decision><StatusMessage/></Result><Session uuid="68FDC91F-3146-436C-BE1D-0C7378A819EF" uconUrl="https://localhost:8090" stateType="PASSIVE" stateName="TRY" customId="ziopino"/></Response></ex:dom></value></param></params></methodResponse>
</record>
<record ms="1392">
<methodCall xmlns:ex="http://ws.apache.org/xmlrpc/namespaces/extensions"><methodName>UConS.endAccess</methodName><params><param><value><ex:nil/></value></param><param><value>ziopino</value></param></params></methodCall>
<methodResponse xmlns:ex="http://ws.apache.org/xmlrpc/namespaces/extensions"><params><param><value><ex:dom><Response xmlns="urn:oasis:names:tc:xacml:3.0:core:schema:wd-17"><Result><Decision>Permit</Decision><StatusMessage/></Result><Session uuid="68FDC91F-3146-436C-BE1D-0C7378A819EF" uconUrl="https://localhost:8090" stateType="END" stateName="DELETED" ms="188" customId="ziopino"/></Response></ex:dom></value></param></params></methodResponse>
</record>
<record ms="1620">
<methodCall xmlns:ex="http://ws.apache.org/xmlrpc/namespaces/extensions"><methodName>UConS.tryAccess</methodName><params><param><value><ex:dom><Request xmlns="urn:oasis:names:tc:xacml:3.0:core:schema:wd-17" ReturnPolicyIdList="false" CombinedDecision="false"><Attributes Category="urn:oasis:names:tc:xacml:3.0:attribute-category:resource"><Attribute Issuer="issuer" IncludeInResult="false" AttributeId="urn:oasis:names:tc:xacml:1.0:resource:resource-id"><AttributeValue DataType="http://www.w3.org/2001/XMLSchema#string"/></Attribute></Attributes><Attributes Category="urn:oasis:names:tc:xacml:1.0:subject-category:access-subject"><Attribute Issuer="issuer" IncludeInResult="false" AttributeId="urn:oasis:names:tc:xacml:1.0:subject:subject-id"><AttributeValue DataType="http://www.w3.org/2001/XMLSchema#string">fedoraRole</AttributeValue></Attribute></Attributes><Attributes Category="urn:oasis:names:tc:xacml:3.0:attribute-category:action"><Attribute Issuer="issuer" IncludeInResult="false" AttributeId="urn:oasis:names:tc:xacml:1.0:action:action-id"><AttributeValue DataType="http://www.w3.org/2001/XMLSchema#string">urn:fedora:names:fedora:2.1:action:id-getDatastreamDissemination</AttributeValue></Attribute></Attributes></Request></ex:dom></value></param><param><value>https://localhost:8091</value></param><param><value>ziopino</value></param></params></methodCall>
<methodResponse xmlns:ex="http://ws.apache.org/xmlrpc/namespaces/extensions"><params><param><value><ex:dom><Response xmlns="urn:oasis:names:tc:xacml:3.0:core:schema:wd-17"><Result><Decision>Permit</Decision><StatusMessage/></Result><Session uuid="E17E1834-B1CA-4616-ADE4-4FF61D56613E" uconUrl="https://localhost:8090" stateType="PASSIVE" stateName="TRY" ms="139" customId="ziopino"/></Response></ex:dom></value></param></params></methodResponse>
</record>
<record ms="1829">
<methodCall xmlns:ex="http://ws.apache.org/xmlrpc/namespaces/extensions"><methodName>UConS.assignCustomId</methodName><params><param><value>E17E1834-B1CA-4616-ADE4-4FF61D56613E</value></param><param><value><ex:nil/></value></param><param><value>ziopino2</value></param></params></methodCall>
<methodResponse xmlns:ex="http://ws.apache.org/xmlrpc/namespaces/extensions"><params><param><value><ex:dom><Response xmlns="urn:oasis:names:tc:xacml:3.0:core:schema:wd-17"><Result><Decision>Permit</Decision><StatusMessage/></Result><Session uuid="E17E1834-B1CA-4616-ADE4-4FF61D56613E" uconUrl="https://localhost:8090" stateType="PASSIVE" stateName="TRY" customId="ziopino2"/></Response></ex:dom></value></param></params></methodResponse>
</record>
<record ms="1855">
<methodCall xmlns:ex="http://ws.apache.org/xmlrpc/namespaces/extensions"><methodName>UConS.endAccess</methodName><params><param><value>E17E1834-B1CA-4616-ADE4-4FF61D56613E</value></param><param><value><ex:nil/></value></param></params></methodCall>
<methodResponse xmlns:ex="http://ws.apache.org/xmlrpc/namespaces/extensions"><params><param><value><ex:dom><Response xmlns="urn:oasis:names:tc:xacml:3.0:core:schema:wd-17"><Result><Decision>Permit</Decision><StatusMessage/></Result><Session uuid="E17E1834-B1CA-4616-ADE4-4FF61D56613E" uconUrl="https://localhost:8090" stateType="END" stateName="DELETED" ms="193" customId="ziopino2"/></Response></ex:dom></value></param></params></methodResponse>
</record>
<record ms="2088">
<methodCall xmlns:ex="http://ws.apache.org/xmlrpc/namespaces/extensions"><methodName>UConS.tryAccess</methodName><params><param><value><ex:dom><Request xmlns="urn:oasis:names:tc:xacml:3.0:core:schema:wd-17" ReturnPolicyIdList="false" CombinedDecision="false"><Attributes Category="urn:oasis:names:tc:xacml:3.0:attribute-category:resource"><Attribute Issuer="issuer" IncludeInResult="false" AttributeId="urn:oasis:names:tc:xacml:1.0:resource:resource-id"><AttributeValue DataType="http://www.w3.org/2001/XMLSchema#string"/></Attribute></Attributes><Attributes Category="urn:oasis:names:tc:xacml:1.0:subject-category:access-subject"><Attribute Issuer="issuer" IncludeInResult="false" AttributeId="urn:oasis:names:tc:xacml:1.0:subject:subject-id"><AttributeValue DataType="http://www.w3.org/2001/XMLSchema#string">fedoraRole</AttributeValue></Attribute></Attributes><Attributes Category="urn:oasis:names:tc:xacml:3.0:attribute-category:action"><Attribute Issuer="issuer" IncludeInResult="false" AttributeId="urn:oasis:names:tc:xacml:1.0:action:action-id"><AttributeValue DataType="http://www.w3.org/2001/XMLSchema#string">urn:fedora:names:fedora:2.1:action:id-getDatastreamDissemination</AttributeValue></Attribute></Attributes></Request></ex:dom></value></param><param><value>https://localhost:8091</value></param><param><value><ex:nil/></value></param></params></methodCall>
<methodResponse xmlns:ex="http://ws.apache.org/xmlrpc/namespaces/extensions"><params><param><value><ex:dom><Response xmlns="urn:oasis:names:tc:xacml:3.0:core:schema:wd-17"><Result><Decision>Permit</Decision><StatusMessage/></Result><Session uuid="EF03AED6-C589-4615-A975-4A2807574F02" uconUrl="https://localhost:8090" stateType="PASSIVE" stateName="TRY" ms="113"/></Response></ex:dom></value></param></params></methodResponse>
</record>
<record ms="2230">
<methodCall xmlns:ex="http://ws.apache.org/xmlrpc/namespaces/extensions"><methodName>UConS.apply</methodName><params><param><value>startAccess</value></param><param><value>EF03AED6-C589-4615-A975-4A2807574F02</value></param><param><value></value></param><param><value><array><data/></array></value></param></params></methodCall>
<methodResponse xmlns:ex="http://ws.apache.org/xmlrpc/namespaces/extensions"><params><param><value><ex:dom><Response xmlns="urn:oasis:names:tc:xacml:3.0:core:schema:wd-17"><Result><Decision>Permit</Decision><StatusMessage/></Result><Session uuid="EF03AED6-C589-4615-A975-4A2807574F02" uconUrl="https://localhost:8090" stateType="ONGOING" stateName="ONGOING" ms="199"/></Response></ex:dom></value></param></params></methodResponse>
</record>
<record ms="2463">
<methodCall xmlns:ex="http://ws.apache.org/xmlrpc/namespaces/extensions"><methodName>UConS.endAccess</methodName><params><param><value>EF03AED6-C589-4615-A975-4A2807574F02</value></param><param><value></value></param></params></methodCall>
<methodResponse xmlns:ex="http://ws.apache.org/xmlrpc/namespaces/extensions"><params><param><value><ex:dom><Response xmlns="urn:oasis:names:tc:xacml:3.0:core:schema:wd-17"><Result><Decision>Permit</Decision><StatusMessage/></Result><Session uuid="EF03AED6-C589-4615-A975-4A2807574F02" uconUrl="https://localhost:8090" stateType="END" stateName="DELETED" ms="92"/></Response></ex:dom></value></param></params></methodResponse>
</record>
<record ms="2608">
<methodCall xmlns:ex="http://ws.apache.org/xmlrpc/namespaces/extensions"><methodName>UConS.tryAccess</methodName><params><param><value><ex:dom><Request xmlns="urn:oasis:names:tc:xacml:3.0:core:schema:wd-17" ReturnPolicyIdList="false" CombinedDecision="false"><Attributes Category="urn:oasis:names:tc:xacml:3.0:attribute-category:resource"><Attribute Issuer="issuer" IncludeInResult="false" AttributeId="urn:oasis:names:tc:xacml:1.0:resource:resource-id"><AttributeValue DataType="http://www.w3.org/2001/XMLSchema#string"/></Attribute></Attributes><Attributes Category="urn:oasis:names:tc:xacml:1.0:subject-category:access-subject"><Attribute Issuer="issuer" IncludeInResult="false" AttributeId="urn:oasis:names:tc:xacml:1.0:subject:subject-id"><AttributeValue DataType="http://www.w3.org/2001/XMLSchema#string">fedoraRole</AttributeValue></Attribute></Attributes><Attributes Category="urn:oasis:names:tc:xacml:3.0:attribute-category:action"><Attribute Issuer="issuer" IncludeInResult="false" AttributeId="urn:oasis:names:tc:xacml:1.0:action:action-id"><AttributeValue DataType="http://www.w3.org/2001/XMLSchema#string">urn:fedora:names:fedora:2.1:action:id-getDatastreamDissemination</AttributeValue></Attribute></Attributes></Request></ex:dom></value></param><param><value>https://localhost:8091</value></param><param><value><ex:nil/></value></param></params></methodCall>
<methodResponse xmlns:ex="http://ws.apache.org/xmlrpc/namespaces/extensions"><params><param><value><ex:dom><Response xmlns="urn:oasis:names:tc:xacml:3.0:core:schema:wd-17"><Result><Decision>Permit</Decision><StatusMessage/></Result><Session uuid="879DC7A4-68B9-41AF-BAA5-37B99F6500F5" uconUrl="https://localhost:8090" stateType="PASSIVE" stateName="TRY" ms="124"/></Response></ex:dom></value></param></params></methodResponse>
</record>
<record ms="2766">
<methodCall xmlns:ex="http://ws.apache.org/xmlrpc/namespaces/extensions"><methodName>UConS.apply</methodName><params><param><value>startAccess</value></param><param><value>879DC7A4-68B9-41AF-BAA5-37B99F6500F5</value></param><param><value></value></param><param><value><array><data/></array></value></param></params></methodCall>
<methodResponse xmlns:ex="http://ws.apache.org/xmlrpc/namespaces/extensions"><params><param><value><ex:dom><Response xmlns="urn:oasis:names:tc:xacml:3.0:core:schema:wd-17"><Result><Decision>Permit</Decision><StatusMessage/></Result><Session uuid="879DC7A4-68B9-41AF-BAA5-37B99F6500F5" uconUrl="https://localhost:8090" stateType="ONGOING" stateName="ONGOING" ms="179"/></Response></ex:dom></value></param></params></methodResponse>
</record>
<record ms="3066">
<methodCall xmlns:ex="http://ws.apache.org/xmlrpc/namespaces/extensions"><methodName>UConS.tryAccess</methodName><params><param><value><ex:dom><Request xmlns="urn:oasis:names:tc:xacml:3.0:core:schema:wd-17" ReturnPolicyIdList="false" CombinedDecision="false"><Attributes Category="urn:oasis:names:tc:xacml:3.0:attribute-category:resource"><Attribute Issuer="issuer" IncludeInResult="false" AttributeId="urn:oasis:names:tc:xacml:1.0:resource:resource-id"><AttributeValue DataType="http://www.w3.org/2001/XMLSchema#string"/></Attribute></Attributes><Attributes Category="urn:oasis:names:tc:xacml:1.0:subject-category:access-subject"><Attribute Issuer="issuer" IncludeInResult="false" AttributeId="urn:oasis:names:tc:xacml:1.0:subject:subject-id"><AttributeValue DataType="http://www.w3.org/2001/XMLSchema#string">fedoraRole</AttributeValue></Attribute></Attributes><Attributes Category="urn:oasis:names:tc:xacml:3.0:attribute-category:action"><Attribute Issuer="issuer" IncludeInResult="false" AttributeId="urn:oasis:names:tc:xacml:1.0:action:action-id"><AttributeValue DataType="http://www.w3.org/2001/XMLSchema#string">urn:fedora:names:fedora:2.1:action:id-getDatastreamDissemination</AttributeValue></Attribute></Attributes></Request></ex:dom></value></param><param><value>https://localhost:8091</value></param><param><value><ex:nil/></value></param></params></methodCall>
<methodResponse xmlns:ex="http://ws.apache.org/xmlrpc/namespaces/extensions"><params><param><value><ex:dom><Response xmlns="urn:oasis:names:tc:xacml:3.0:core:schema:wd-17"><Result><Decision>Permit</Decision><StatusMessage/></Result><Session uuid="8F8620E4-09F6-4AE0-AF54-543B4DE53512" uconUrl="https://localhost:8090" stateType="PASSIVE" stateName="TRY" ms="46"/></Response></ex:dom></value></param></params></methodResponse>
</record>
<record ms="3140">
<methodCall xmlns:ex="http://ws.apache.org/xmlrpc/namespaces/extensions"><methodName>UConS.apply</methodName><params><param><value>startAccess</value></param><param><value>8F8620E4-09F6-4AE0-AF54-543B4DE53512</value></param><param><value></value></param><param><value><array><data/></array></value></param></params></methodCall>
<methodResponse xmlns:ex="http://ws.apache.org/xmlrpc/namespaces/extensions"><params><param><value><ex:dom><Response xmlns="urn:oasis:names:tc:xacml:3.0:core:schema:wd-17"><Result><Decision>Permit</Decision><StatusMessage/></Result><Session uuid="8F8620E4-09F6-4AE0-AF54-543B4DE53512" uconUrl="https://localhost:8090" stateType="ONGOING" stateName="ONGOING" ms="54"/></Response></ex:dom></value></param></params></methodResponse>
</record>
<record ms="3228">
<methodCall xmlns:ex="http://ws.apache.org/xmlrpc/namespaces/extensions"><methodName>UConS.endAccess</methodName><params><param><value><array><data><value>879DC7A4-68B9-41AF-BAA5-37B99F6500F5</value><value>8F8620E4-09F6-4AE0-AF54-543B4DE53512</value></data></array></value></param><param><value><array><data><value></value><value></value></data></array></value></param></params></methodCall>
<methodResponse xmlns:ex="http://ws.apache.org/xmlrpc/namespaces/extensions"><params><param><value><array><data><value><ex:dom><Response xmlns="urn:oasis:names:tc:xacml:3.0:core:schema:wd-17"><Result><Decision>Permit</Decision><StatusMessage/></Result><Session uuid="879DC7A4-68B9-41AF-BAA5-37B99F6500F5" uconUrl="https://localhost:8090" stateType="END" stateName="DELETED" ms="53"/></Response></ex:dom></value><value><ex:dom><Response xmlns="urn:oasis:names:tc:xacml:3.0:core:schema:wd-17"><Result><Decision>Permit</Decision><StatusMessage/></Result><Session uuid="8F8620E4-09F6-4AE0-AF54-543B4DE53512" uconUrl="https://localhost:8090" stateType="END" stateName="DELETED" ms="166"/></Response></ex:dom></value></data></array></value></param></params></methodResponse>
</record>
<record ms="3492">
<methodCall xmlns:ex="http://ws.apache.org/xmlrpc/namespaces/extensions"><methodName>UConS.tryAccess</methodName><params><param><value><ex:dom><Request xmlns="urn:oasis:names:tc:xacml:3.0:core:schema:wd-17" ReturnPolicyIdList="false" CombinedDecision="false"><Attributes Category="urn:oasis:names:tc:xacml:3.0:attribute-category:resource"><Attribute Issuer="issuer" IncludeInResult="false" AttributeId="urn:oasis:names:tc:xacml:1.0:resource:resource-id"><AttributeValue DataType="http://www.w3.org/2001/XMLSchema#string"/></Attribute></Attributes><Attributes Category="urn:oasis:names:tc:xacml:1.0:subject-category:access-subject"><Attribute Issuer="issuer" IncludeInResult="false" AttributeId="urn:oasis:names:tc:xacml:1.0:subject:subject-id"><AttributeValue DataType="http://www.w3.org/2001/XMLSchema#string">fedoraRole</AttributeValue></Attribute></Attributes><Attributes Category="urn:oasis:names:tc:xacml:3.0:attribute-category:action"><Attribute Issuer="issuer" IncludeInResult="false" AttributeId="urn:oasis:names:tc:xacml:1.0:action:action-id"><AttributeValue DataType="http://www.w3.org/2001/XMLSchema#string">urn:fedora:names:fedora:2.1:action:id-getDatastreamDissemination</AttributeValue></Attribute></Attributes></Request></ex:dom></value></param><param><value>https://localhost:8091</value></param><param><value><ex:nil/></value></param></params></methodCall>
<methodResponse xmlns:ex="http://ws.apache.org/xmlrpc/namespaces/extensions"><params><param><value><ex:dom><Response xmlns="urn:oasis:names:tc:xacml:3.0:core:schema:wd-17"><Result><Decision>Permit</Decision><StatusMessage/></Result><Session uuid="9F7FF944-05D9-4157-B768-5EFE5D7C7654" uconUrl="https://localhost:8090" stateType="PASSIVE" stateName="TRY" ms="119"/></Response></ex:dom></value></param></params></methodResponse>
</record>
<record ms="3650">
<methodCall xmlns:ex="http://ws.apache.org/xmlrpc/namespaces/extensions"><methodName>UConS.assignCustomId</methodName><params><param><value>9F7FF944-05D9-4157-B768-5EFE5D7C7654</value></param><param><value><ex:nil/></value></param><param><value>ziopinetto</value></param></params></methodCall>
<methodResponse xmlns:ex="http://ws.apache.org/xmlrpc/namespaces/extensions"><params><param><value><ex:dom><Response xmlns="urn:oasis:names:tc:xacml:3.0:core:schema:wd-17"><Result><Decision>Permit</Decision><StatusMessage/></Result><Session uuid="9F7FF944-05D9-4157-B768-5EFE5D7C7654" uconUrl="https://localhost:8090" stateType="PASSIVE" stateName="TRY" customId="ziopinetto"/></Response></ex:dom></value></param></params></methodResponse>
</record>
<record ms="3663">
<methodCall xmlns:ex="http://ws.apache.org/xmlrpc/namespaces/extensions"><methodName>UConS.apply</methodName><params><param><value>startAccess</value></param><param><value><ex:nil/></value></param><param><value>ziopinetto</value></param><param><value><array><data/></array></value></param></params></methodCall>
<methodResponse xmlns:ex="http://ws.apache.org/xmlrpc/namespaces/extensions"><params><param><value><ex:dom><Response xmlns="urn:oasis:names:tc:xacml:3.0:core:schema:wd-17"><Result><Decision>Permit</Decision><StatusMessage/></Result><Session uuid="9F7FF944-05D9-4157-B768-5EFE5D7C7654" uconUrl="https://localhost:8090" stateType="ONGOING" stateName="ONGOING" ms="153" customId="ziopinetto"/></Response></ex:dom></value></param></params></methodResponse>
</record>
<record ms="3845">
<methodCall xmlns:ex="http://ws.apache.org/xmlrpc/namespaces/extensions"><methodName>UConS.endAccess</methodName><params><param><value><ex:nil/></value></param><param><value>ziopinetto</value></param></params></methodCall>
<methodResponse xmlns:ex="http://ws.apache.org/xmlrpc/namespaces/extensions"><params><param><value><ex:dom><Response xmlns="urn:oasis:names:tc:xacml:3.0:core:schema:wd-17"><Result><Decision>Permit</Decision><StatusMessage/></Result><Session uuid="9F7FF944-05D9-4157-B768-5EFE5D7C7654" uconUrl="https://localhost:8090" stateType="END" stateName="DELETED" ms="59" customId="ziopinetto"/></Response></ex:dom></value></param></params></methodResponse>
</record>
<record ms="3934">
<methodCall xmlns:ex="http://ws.apache.org/xmlrpc/namespaces/extensions"><methodName>UConS.tryAccess</methodName><params><param><value><ex:dom><Request xmlns="urn:oasis:names:tc:xacml:3.0:core:schema:wd-17" ReturnPolicyIdList="false" CombinedDecision="false"><Attributes Category="urn:oasis:names:tc:xacml:3.0:attribute-category:resource"><Attribute Issuer="issuer" IncludeInResult="false" AttributeId="urn:oasis:names:tc:xacml:1.0:resource:resource-id"><AttributeValue DataType="http://www.w3.org/2001/XMLSchema#string"/></Attribute></Attributes><Attributes Category="urn:oasis:names:tc:xacml:1.0:subject-category:access-subject"><Attribute Issuer="issuer" IncludeInResult="false" AttributeId="urn:oasis:names:tc:xacml:1.0:subject:subject-id"><AttributeValue DataType="http://www.w3.org/2001/XMLSchema#string">fedoraRole</AttributeValue></Attribute></Attributes><Attributes Category="urn:oasis:names:tc:xacml:3.0:attribute-category:action"><Attribute Issuer="issuer" IncludeInResult="false" AttributeId="urn:oasis:names:tc:xacml:1.0:action:action-id"><AttributeValue DataType="http://www.w3.org/2001/XMLSchema#string">urn:fedora:names:fedora:2.1:action:id-getDatastreamDissemination</AttributeValue></Attribute></Attributes></Request></ex:dom></value></param><param><value>https://localhost:8091</value></param><param><value><ex:nil/></value></param></params></methodCall>
<methodResponse xmlns:ex="http://ws.apache.org/xmlrpc/namespaces/extensions"><params><param><value><ex:dom><Response xmlns="urn:oasis:names:tc:xacml:3.0:core:schema:wd-17"><Result><Decision>Permit</Decision><StatusMessage/></Result><Session uuid="B174B9BE-0B04-4AD9-82FD-83B0A78A1915" uconUrl="https://localhost:8090" stateType="PASSIVE" stateName="TRY" ms="119"/></Response></ex:dom></value></param></params></methodResponse>
</record>
<record ms="4080">
<methodCall xmlns:ex="http://ws.apache.org/xmlrpc/namespaces/extensions"><methodName>UConS.apply</methodName><params><param><value>startAccess</value></param><param><value>B174B9BE-0B04-4AD9-82FD-83B0A78A1915</value></param><param><value><ex:nil/></value></param><param><value><array><data/></array></value></param></params></methodCall>
<methodResponse xmlns:ex="http://ws.apache.org/xmlrpc/namespaces/extensions"><params><param><value><ex:dom><Response xmlns="urn:oasis:names:tc:xacml:3.0:core:schema:wd-17"><Result><Decision>Permit</Decision><StatusMessage/></Result><Session uuid="B174B9BE-0B04-4AD9-82FD-83B0A78A1915" uconUrl="https://localhost:8090" stateType="ONGOING" stateName="ONGOING" ms="150"/></Response></ex:dom></value></param></params></methodResponse>
</record>
<record ms="4258">
<methodCall xmlns:ex="http://ws.apache.org/xmlrpc/namespaces/extensions"><methodName>UConS.endAccess</methodName><params><param><value>B174B9BE-0B04-4AD9-82FD-83B0A78A1915</value></param><param><value><ex:nil/></value></param></params></methodCall>
<methodResponse xmlns:ex="http://ws.apache.org/xmlrpc/namespaces/extensions"><params><param><value><ex:dom><Response xmlns="urn:oasis:names:tc:xacml:3.0:core:schema:wd-17"><Result><Decision>Permit</Decision><StatusMessage/></Result><Session uuid="B174B9BE-0B04-4AD9-82FD-83B0A78A1915" uconUrl="https://localhost:8090" stateType="END" stateName="DELETED" ms="49"/></Response></ex:dom></value></param></params></methodResponse>
</record>
<record ms="4337">
<methodCall xmlns:ex="http://ws.apache.org/xmlrpc/namespaces/extensions"><methodName>UConS.apply</methodName><params><param><value>startAccess</value></param><param><value>unexistentUuid</value></param><param><value><ex:nil/></value></param><param><value><array><data/></array></value></param></params></methodCall>
<methodResponse xmlns:ex="http://ws.apache.org/xmlrpc/namespaces/extensions"><fault><value><struct><member><name>faultCode</name><value><i4>0</i4></value></member><member><name>faultString</name><value>Failed to invoke method apply in class it.cnr.iit.retrail.server.impl.UConProtocolProxy: Session with uuid=unexistentUuid is unknown</value></member></struct></value></fault></methodResponse>
</record>
<record ms="4346">
<methodCall xmlns:ex="http://ws.apache.org/xmlrpc/namespaces/extensions"><methodName>UConS.apply</methodName><params><param><value>startAccess</value></param><param><value><ex:nil/></value></param><param><value>unexistentCustomId</value></param><param><value><array><data/></array></value></param></params></methodCall>
<methodResponse xmlns:ex="http://ws.apache.org/xmlrpc/namespaces/extensions"><fault><value><struct><member><name>faultCode</name><value><i4>0</i4></value></member><member><name>faultString</name><value>Failed to invoke method apply in class it.cnr.iit.retrail.server.impl.UConProtocolProxy: getSingleResult() did not retrieve any entities.</value></member></struct></value></fault></methodResponse>
</record>
<record ms="4356">
<methodCall xmlns:ex="http://ws.apache.org/xmlrpc/namespaces/extensions"><methodName>UConS.apply</methodName><params><param><value>startAccess</value></param><param><value><ex:nil/></value></param><param><value></value></param><param><value><array><data/></array></value></param></params></methodCall>
<methodResponse xmlns:ex="http://ws.apache.org/xmlrpc/namespaces/extensions"><fault><value><struct><member><name>faultCode</name><value><i4>0</i4></value></member><member><name>faultString</name><value>Failed to invoke method apply in class it.cnr.iit.retrail.server.impl.UConProtocolProxy: getSingleResult() did not retrieve any entities.</value></member></struct></value></fault></methodResponse>
</record>
<record ms="4364">
<methodCall xmlns:ex="http://ws.apache.org/xmlrpc/namespaces/extensions"><methodName>UConS.apply</methodName><params><param><value>startAccess</value></param><param><value><ex:nil/></value></param><param><value><ex:nil/></value></param><param><value><array><data/></array></value></param></params></methodCall>
<methodResponse xmlns:ex="http://ws.apache.org/xmlrpc/namespaces/extensions"><fault><value><struct><member><name>faultCode</name><value><i4>0</i4></value></member><member><name>faultString</name><value>Failed to invoke method apply in class it.cnr.iit.retrail.server.impl.UConProtocolProxy: null</value></member></struct></value></fault></methodResponse>
</record>
<record ms="4373">
<methodCall xmlns:ex="http://ws.apache.org/xmlrpc/namespaces/extensions"><methodName>UConS.apply</methodName><params><param><value>startAccess</value></param><param><value></value></param><param><value><ex:nil/></value></param><param><value><array><data/></array></value></param></params></methodCall>
<methodResponse xmlns:ex="http://ws.apache.org/xmlrpc/namespaces/extensions"><fault><value><struct><member><name>faultCode</name><value><i4>0</i4></value></member><member><name>faultString</name><value>Failed to invoke method apply in class it.cnr.iit.retrail.server.impl.UConProtocolProxy: Session with uuid= is unknown</value></member></struct></value></fault></methodResponse>
</record>
<record ms="4381">
<methodCall xmlns:ex="http://ws.apache.org/xmlrpc/namespaces/extensions"><methodName>UConS.endAccess</methodName><params><param><value>unexistentUuid</value></param><param><value><ex:nil/></value></param></params></methodCall>
<methodResponse xmlns:ex="http://ws.apache.org/xmlrpc/namespaces/extensions"><fault><value><struct><member><name>faultCode</name><value><i4>0</i4></value></member><member><name>faultString</name><value>Failed to invoke method endAccess in class it.cnr.iit.retrail.server.impl.UConProtocolProxy: Session with uuid=unexistentUuid is unknown</value></member></struct></value></fault></methodResponse>
</record>
<record ms="4389">
<methodCall xmlns:ex="http://ws.apache.org/xmlrpc/namespaces/extensions"><methodName>UConS.endAccess</methodName><params><param><value><ex:nil/></value></param><param><value>badCustomId</value></param></params></methodCall>
<methodResponse xmlns:ex="http://ws.apache.org/xmlrpc/namespaces/extensions"><fault><value><struct><member><name>faultCode</name><value><i4>0</i4></value></member><member><name>faultString</name><value>Failed to invoke method endAccess in class it.cnr.iit.retrail.server.impl.UConProtocolProxy: getSingleResult() did not retrieve any entities.</value></member></struct></value></fault></methodResponse>
</record>
<record ms="4397">
<methodCall xmlns:ex="http://ws.apache.org/xmlrpc/namespaces/extensions"><methodName>UConS.endAccess</methodName><params><param><value><ex:nil/></value></param><param><value></value></param></params></methodCall>
<methodResponse xmlns:ex="http://ws.apache.org/xmlrpc/namespaces/extensions"><fault><value><struct><member><name>faultCode</name><value><i4>0</i4></value></member><member><name>faultString</name><value>Failed to invoke method endAccess in class it.cnr.iit.retrail.server.impl.UConProtocolProxy: getSingleResult() did not retrieve any entities.</value></member></struct></value></fault></methodResponse>
</record>
<record ms="4404">
<methodCall xmlns:ex="http://ws.apache.org/xmlrpc/namespaces/extensions"><methodName>UConS.endAccess</methodName><params><param><value></value></param><param><value><ex:nil/></value></param></params></methodCall>
<methodResponse xmlns:ex="http://ws.apache.org/xmlrpc/namespaces/extensions"><fault><value><struct><member><name>faultCode</name><value><i4>0</i4></value></member><member><name>faultString</name><value>Failed to invoke method endAccess in class it.cnr.iit.retrail.server.impl.UConProtocolProxy: Session with uuid= is unknown</value></member></struct></value></fault></methodResponse>
</record>
<record ms="4412">
<methodCall xmlns:ex="http://ws.apache.org/xmlrpc/namespaces/extensions"><methodName>UConS.endAccess</methodName><params><param><value><ex:nil/></value></param><param><value><ex:nil/></value></param></params></methodCall>
<methodResponse xmlns:ex="http://ws.apache.org/xmlrpc/namespaces/extensions"><fault><value><struct><member><name>faultCode</name><value><i4>0</i4></value></member><member><name>faultString</name><value>Failed to invoke method endAccess in class it.cnr.iit.retrail.server.impl.UConProtocolProxy: null</value></member></struct></value></fault></methodResponse>
</record>
<record ms="4489">
<methodCall xmlns:ex="http://ws.apache.org/xmlrpc/namespaces/extensions"><methodName>UConS.endAccess</methodName><params><param><value><ex:nil/></value></param><param><value><ex:nil/></value></param></params></methodCall>
<methodResponse xmlns:ex="http://ws.apache.org/xmlrpc/namespaces/extensions"><fault><value><struct><member><name>faultCode</name><value><i4>0</i4></value></member><member><name>faultString</name><value>Failed to invoke method endAccess in class it.cnr.iit.retrail.server.impl.UConProtocolProxy: null</value></member></struct></value></fault></methodResponse>
</record>
<record ms="4500">
<methodCall xmlns:ex="http://ws.apache.org/xmlrpc/namespaces/extensions"><methodName>UConS.assignCustomId</methodName><params><param><value>unexistentUuid</value></param><param><value><ex:nil/></value></param><param><value><ex:nil/></value></param></params></methodCall>
<methodResponse xmlns:ex="http://ws.apache.org/xmlrpc/namespaces/extensions"><fault><value><struct><member><name>faultCode</name><value><i4>0</i4></value></member><member><name>faultString</name><value>Failed to invoke method assignCustomId in class it.cnr.iit.retrail.server.impl.UConProtocolProxy: null or empty customId for: unexistentUuid</value></member></struct></value></fault></methodResponse>
</record>
<record ms="4510">
<methodCall xmlns:ex="http://ws.apache.org/xmlrpc/namespaces/extensions"><methodName>UConS.tryAccess</methodName><params><param><value><ex:dom><Request xmlns="urn:oasis:names:tc:xacml:3.0:core:schema:wd-17" ReturnPolicyIdList="false" CombinedDecision="false"><Attributes Category="urn:oasis:names:tc:xacml:3.0:attribute-category:resource"><Attribute Issuer="issuer" IncludeInResult="false" AttributeId="urn:oasis:names:tc:xacml:1.0:resource:resource-id"><AttributeValue DataType="http://www.w3.org/2001/XMLSchema#string"/></Attribute></Attributes><Attributes Category="urn:oasis:names:tc:xacml:1.0:subject-category:access-subject"><Attribute Issuer="issuer" IncludeInResult="false" AttributeId="urn:oasis:names:tc:xacml:1.0:subject:subject-id"><AttributeValue DataType="http://www.w3.org/2001/XMLSchema#string">fedoraRole</AttributeValue></Attribute></Attributes><Attributes Category="urn:oasis:names:tc:xacml:3.0:attribute-category:action"><Attribute Issuer="issuer" IncludeInResult="false" AttributeId="urn:oasis:names:tc:xacml:1.0:action:action-id"><AttributeValue DataType="http://www.w3.org/2001/XMLSchema#string">urn:fedora:names:fedora:2.1:action:id-getDatastreamDissemination</AttributeValue></Attribute></Attributes></Request></ex:dom></value></param><param><value>https://localhost:8091</value></param><param><value><ex:nil/></value></param></params></methodCall>
<methodResponse xmlns:ex="http://ws.apache.org/xmlrpc/namespaces/extensions"><params><param><value><ex:dom><Response xmlns="urn:oasis:names:tc:xacml:3.0:core:schema:wd-17"><Result><Decision>Permit</Decision><StatusMessage/></Result><Session uuid="FD43D147-12F5-446F-8B76-13C9B33A2D1D" uconUrl="https://localhost:8090" stateType="PASSIVE" stateName="TRY" ms="147"/></Response></ex:dom></value></param></params></methodResponse>
</record>
<record ms="4690">
<methodCall xmlns:ex="http://ws.apache.org/xmlrpc/namespaces/extensions"><methodName>UConS.assignCustomId</methodName><params><param><value>FD43D147-12F5-446F-8B76-13C9B33A2D1D</value></param><param><value><ex:nil/></value></param><param><value><ex:nil/></value></param></params></methodCall>
<methodResponse xmlns:ex="http://ws.apache.org/xmlrpc/namespaces/extensions"><fault><value><struct><member><name>faultCode</name><value><i4>0</i4></value></member><member><name>faultString</name><value>Failed to invoke method assignCustomId in class it.cnr.iit.retrail.server.impl.UConProtocolProxy: null or empty customId for: FD43D147-12F5-446F-8B76-13C9B33A2D1D</value></member></struct></value></fault></methodResponse>
</record>
<record ms="4698">
<methodCall xmlns:ex="http://ws.apache.org/xmlrpc/namespaces/extensions"><methodName>UConS.endAccess</methodName><params><param><value>FD43D147-12F5-446F-8B76-13C9B33A2D1D</value></param><param><value></value></param></params></methodCall>
<methodResponse xmlns:ex="http://ws.apache.org/xmlrpc/namespaces/extensions"><params><param><value><ex:dom><Response xmlns="urn:oasis:names:tc:xacml:3.0:core:schema:wd-17"><Result><Decision>Permit</Decision><StatusMessage/></Result><Session uuid="FD43D147-12F5-446F-8B76-13C9B33A2D1D" uconUrl="https://localhost:8090" stateType="END" stateName="DELETED" ms="158"/></Response></ex:dom></value></param></params></methodResponse>
</record>
<record ms="4878">
<methodCall xmlns:ex="http://ws.apache.org/xmlrpc/namespaces/extensions"><methodName>UConS.tryAccess</methodName><params><param><value><ex:dom><Request xmlns="urn:oasis:names:tc:xacml:3.0:core:schema:wd-17" ReturnPolicyIdList="false" CombinedDecision="false"><Attributes Category="urn:oasis:names:tc:xacml:3.0:attribute-category:resource"><Attribute Issuer="issuer" IncludeInResult="false" AttributeId="urn:oasis:names:tc:xacml:1.0:resource:resource-id"><AttributeValue DataType="http://www.w3.org/2001/XMLSchema#string"/></Attribute></Attributes><Attributes Category="urn:oasis:names:tc:xacml:1.0:subject-category:access-subject"><Attribute Issuer="issuer" IncludeInResult="false" AttributeId="urn:oasis:names:tc:xacml:1.0:subject:subject-id"><AttributeValue DataType="http://www.w3.org/2001/XMLSchema#string">fedoraRole</AttributeValue></Attribute></Attributes><Attributes Category="urn:oasis:names:tc:xacml:3.0:attribute-category:action"><Attribute Issuer="issuer" IncludeInResult="false" AttributeId="urn:oasis:names:tc:xacml:1.0:action:action-id"><AttributeValue DataType="http://www.w3.org/2001/XMLSchema#string">urn:fedora:names:fedora:2.1:action:id-getDatastreamDissemination</AttributeValue></Attribute></Attributes></Request></ex:dom></value></param><param><value>https://localhost:8091</value></param><param><value>ziopino5</value></param></params></methodCall>
<methodResponse xmlns:ex="http://ws.apache.org/xmlrpc/namespaces/extensions"><params><param><value><ex:dom><Response xmlns="urn:oasis:names:tc:xacml:3.0:core:schema:wd-17"><Result><Decision>Permit</Decision><StatusMessage/></Result><Session uuid="4DECC4D4-1268-49D3-B8B6-DFE44638A755" uconUrl="https://localhost:8090" stateType="PASSIVE" stateName="TRY" ms="123" customId="ziopino5"/></Response></ex:dom></value></param></params></methodResponse>
</record>
<record ms="5029">
<methodCall xmlns:ex="http://ws.apache.org/xmlrpc/namespaces/extensions"><methodName>UConS.assignCustomId</methodName><params><param><value><ex:nil/></value></param><param><value>ziopino5</value></param><param><value>ziopino23</value></param></params></methodCall>
<methodResponse xmlns:ex="http://ws.apache.org/xmlrpc/namespaces/extensions"><params><param><value><ex:dom><Response xmlns="urn:oasis:names:tc:xacml:3.0:core:schema:wd-17"><Result><Decision>Permit</Decision><StatusMessage/></Result><Session uuid="4DECC4D4-1268-49D3-B8B6-DFE44638A755" uconUrl="https://localhost:8090" stateType="PASSIVE" stateName="TRY" customId="ziopino23"/></Response></ex:dom></value></param></params></methodResponse>
</record>
<record ms="5039">
<methodCall xmlns:ex="http://ws.apache.org/xmlrpc/namespaces/extensions"><methodName>UConS.endAccess</methodName><params><param><value><ex:nil/></value></param><param><value>ziopino23</value></param></params></methodCall>
<methodResponse xmlns:ex="http://ws.apache.org/xmlrpc/namespaces/extensions"><params><param><value><ex:dom><Response xmlns="urn:oasis:names:tc:xacml:3.0:core:schema:wd-17"><Result><Decision>Permit</Decision><StatusMessage/></Result><Session uuid="4DECC4D4-1268-49D3-B8B6-DFE44638A755" uconUrl="https://localhost:8090" stateType="END" stateName="DELETED" ms="143" customId="ziopino23"/></Response></ex:dom></value></param></params></methodResponse>
</record>
<record ms="5203">
<methodCall xmlns:ex="http://ws.apache.org/xmlrpc/namespaces/extensions"><methodName>UConS.tryAccess</methodName><params><param><value><ex:dom><Request xmlns="urn:oasis:names:tc:xacml:3.0:core:schema:wd-17" ReturnPolicyIdList="false" CombinedDecision="false"><Attributes Category="urn:oasis:names:tc:xacml:3.0:attribute-category:resource"><Attribute Issuer="issuer" IncludeInResult="false" AttributeId="urn:oasis:names:tc:xacml:1.0:resource:resource-id"><AttributeValue DataType="http://www.w3.org/2001/XMLSchema#string"/></Attribute></Attributes><Attributes Category="urn:oasis:names:tc:xacml:1.0:subject-category:access-subject"><Attribute Issuer="issuer" IncludeInResult="false" AttributeId="urn:oasis:names:tc:xacml:1.0:subject:subject-id"><AttributeValue DataType="http://www.w3.org/2001/XMLSchema#string">fedoraRole</AttributeValue></Attribute></Attributes><Attributes Category="urn:oasis:names:tc:xacml:3.0:attribute-category:action"><Attribute Issuer="issuer" IncludeInResult="false" AttributeId="urn:oasis:names:tc:xacml:1.0:action:action-id"><AttributeValue DataType="http://www.w3.org/2001/XMLSchema#string">urn:fedora:names:fedora:2.1:action:id-getDatastreamDissemination</AttributeValue></Attribute></Attributes></Request></ex:dom></value></param><param><value>https://localhost:8091</value></param><param><value><ex:nil/></value></param></params></methodCall>
<methodResponse xmlns:ex="http://ws.apache.org/xmlrpc/namespaces/extensions"><params><param><value><ex:dom><Response xmlns="urn:oasis:names:tc:xacml:3.0:core:schema:wd-17"><Result><Decision>Permit</Decision><StatusMessage/></Result><Session uuid="454F9CF9-ADC7-4FD4-9E69-20210AF9D057" uconUrl="https://localhost:8090" stateType="PASSIVE" stateName="TRY" ms="115"/></Response></ex:dom></value></param></params></methodResponse>
</record>
<record ms="5346">
<methodCall xmlns:ex="http://ws.apache.org/xmlrpc/namespaces/extensions"><methodName>UConS.apply</methodName><params><param><value>startAccess</value></param><param><value>454F9CF9-ADC7-4FD4-9E69-20210AF9D057</value></param><param><value></value></param><param><value><array><data/></array></value></param></params></methodCall>
<methodResponse xmlns:ex="http://ws.apache.org/xmlrpc/namespaces/extensions"><params><param><value><ex:dom><Response xmlns="urn:oasis:names:tc:xacml:3.0:core:schema:wd-17"><Result><Decision>Permit</Decision><StatusMessage/></Result><Session uuid="454F9CF9-ADC7-4FD4-9E69-20210AF9D057" uconUrl="https://localhost:8090" stateType="ONGOING" stateName="ONGOING" ms="141"/></Response></ex:dom></value></param></params></methodResponse>
</record>
<record ms="5518">
<methodCall xmlns:ex="http://ws.apache.org/xmlrpc/namespaces/extensions"><methodName>UConS.apply</methodName><params><param><value>startAccess</value></param><param><value>454F9CF9-ADC7-4FD4-9E69-20210AF9D057</value></param><param><value></value></param><param><value><array><data/></array></value></param></params></methodCall>
<methodResponse xmlns:ex="http://ws.apache.org/xmlrpc/namespaces/extensions"><fault><value><struct><member><name>faultCode</name><value><i4>0</i4></value></member><member><name>faultString</name><value>Failed to invoke method apply in class it.cnr.iit.retrail.server.impl.UConProtocolProxy: while executing action startAccess</value></member></struct></value></fault></methodResponse>
</record>
<record ms="5559">
<methodCall xmlns:ex="http://ws.apache.org/xmlrpc/namespaces/extensions"><methodName>UConS.endAccess</methodName><params><param><value>454F9CF9-ADC7-4FD4-9E69-20210AF9D057</value></param><param><value></value></param></params></methodCall>
<methodResponse xmlns:ex="http://ws.apache.org/xmlrpc/namespaces/extensions"><params><param><value><ex:dom><Response xmlns="urn:oasis:names:tc:xacml:3.0:core:schema:wd-17"><Result><Decision>Permit</Decision><StatusMessage/></Result><Session uuid="454F9CF9-ADC7-4FD4-9E69-20210AF9D057" uconUrl="https://localhost:8090" stateType="END" stateName="DELETED" ms="44"/></Response></ex:dom></value></param></params></methodResponse>
</record>
<record ms="5633">
<methodCall xmlns:ex="http://ws.apache.org/xmlrpc/namespaces/extensions"><methodName>UConS.tryAccess</methodName><params><param><value><ex:dom><Request xmlns="urn:oasis:names:tc:xacml:3.0:core:schema:wd-17" ReturnPolicyIdList="false" CombinedDecision="false"><Attributes Category="urn:oasis:names:tc:xacml:3.0:attribute-category:resource"><Attribute Issuer="issuer" IncludeInResult="false" AttributeId="urn:oasis:names:tc:xacml:1.0:resource:resource-id"><AttributeValue DataType="http://www.w3.org/2001/XMLSchema#string"/></Attribute></Attributes><Attributes Category="urn:oasis:names:tc:xacml:1.0:subject-category:access-subject"><Attribute Issuer="issuer" IncludeInResult="false" AttributeId="urn:oasis:names:tc:xacml:1.0:subject:subject-id"><AttributeValue DataType="http://www.w3.org/2001/XMLSchema#string">fedoraRole</AttributeValue></Attribute></Attributes><Attributes Category="urn:oasis:names:tc:xacml:3.0:attribute-category:action"><Attribute Issuer="issuer" IncludeInResult="false" AttributeId="urn:oasis:names:tc:xacml:1.0:action:action-id"><AttributeValue DataType="http://www.w3.org/2001/XMLSchema#string">urn:fedora:names:fedora:2.1:action:id-getDatastreamDissemination</AttributeValue></Attribute></Attributes></Request></ex:dom></value></param><param><value>https://localhost:8091</value></param><param><value><ex:nil/></value></param></params></methodCall>
<methodResponse xmlns:ex="http://ws.apache.org/xmlrpc/namespaces/extensions"><params><param><value><ex:dom><Response xmlns="urn:oasis:names:tc:xacml:3.0:core:schema:wd-17"><Result><Decision>Permit</Decision><StatusMessage/></Result><Session uuid="914A0943-6C4B-4803-B379-267712D13891" uconUrl="https://localhost:8090" stateType="PASSIVE" stateName="TRY" ms="114"/></Response></ex:dom></value></param></params></methodResponse>
</record>
<record ms="5781">
<methodCall xmlns:ex="http://ws.apache.org/xmlrpc/namespaces/extensions"><methodName>UConS.apply</methodName><params><param><value>startAccess</value></param><param><value>914A0943-6C4B-4803-B379-267712D13891</value></param><param><value></value></param><param><value><array><data/></array></value></param></params></methodCall>
<methodResponse xmlns:ex="http://ws.apache.org/xmlrpc/namespaces/extensions"><params><param><value><ex:dom><Response xmlns="urn:oasis:names:tc:xacml:3.0:core:schema:wd-17"><Result><Decision>Permit</Decision><StatusMessage/></Result><Session uuid="914A0943-6C4B-4803-B379-267712D13891" uconUrl="https://localhost:8090" stateType="ONGOING" stateName="ONGOING" ms="315"/></Response></ex:dom></value></param></params></methodResponse>
</record>
<record ms="6142">
<methodCall xmlns:ex="http://ws.apache.org/xmlrpc/namespaces/extensions"><methodName>UConS.endAccess</methodName><params><param><value>914A0943-6C4B-4803-B379-267712D13891</value></param><param><value></value></param></params></methodCall>
<methodResponse xmlns:ex="http://ws.apache.org/xmlrpc/namespaces/extensions"><params><param><value><ex:dom><Response xmlns="urn:oasis:names:tc:xacml:3.0:core:schema:wd-17"><Result><Decision>Permit</Decision><StatusMessage/></Result><Session uuid="914A0943-6C4B-4803-B379-267712D13891" uconUrl="https://localhost:8090" stateType="END" stateName="DELETED" ms="48"/></Response></ex:dom></value></param></params></methodResponse>
</record>
<record ms="6213">
<methodCall xmlns:ex="http://ws.apache.org/xmlrpc/namespaces/extensions"><methodName>UConS.tryAccess</methodName><params><param><value><ex:dom><Request xmlns="urn:oasis:names:tc:xacml:3.0:core:schema:wd-17" ReturnPolicyIdList="false" CombinedDecision="false"><Attributes Category="urn:oasis:names:tc:xacml:3.0:attribute-category:resource"><Attribute Issuer="issuer" IncludeInResult="false" AttributeId="urn:oasis:names:tc:xacml:1.0:resource:resource-id"><AttributeValue DataType="http://www.w3.org/2001/XMLSchema#string"/></Attribute></Attributes><Attributes Category="urn:oasis:names:tc:xacml:1.0:subject-category:access-subject"><Attribute Issuer="issuer" IncludeInResult="false" AttributeId="urn:oasis:names:tc:xacml:1.0:subject:subject-id"><AttributeValue DataType="http://www.w3.org/2001/XMLSchema#string">fedoraRole</AttributeValue></Attribute></Attributes><Attributes Category="urn:oasis:names:tc:xacml:3.0:attribute-category:action"><Attribute Issuer="issuer" IncludeInResult="false" AttributeId="urn:oasis:names:tc:xacml:1.0:action:action-id"><AttributeValue DataType="http://www.w3.org/2001/XMLSchema#string">urn:fedora:names:fedora:2.1:action:id-getDatastreamDissemination</AttributeValue></Attribute></Attributes></Request></ex:dom></value></param><param><value>https://localhost:8091</value></param><param><value><ex:nil/></value></param></params></methodCall>
<methodResponse xmlns:ex="http://ws.apache.org/xmlrpc/namespaces/extensions"><params><param><value><ex:dom><Response xmlns="urn:oasis:names:tc:xacml:3.0:core:schema:wd-17"><Result><Decision>Permit</Decision><StatusMessage/></Result><Session uuid="1987A4B8-97AA-4F03-AE21-87F6F40632A7" uconUrl="https://localhost:8090" stateType="PASSIVE" stateName="TRY" ms="111"/></Response></ex:dom></value></param></params></methodResponse>
</record>
<record ms="6353">
<methodCall xmlns:ex="http://ws.apache.org/xmlrpc/namespaces/extensions"><methodName>UConS.tryAccess</methodName><params><param><value><ex:dom><Request xmlns="urn:oasis:names:tc:xacml:3.0:core:schema:wd-17" ReturnPolicyIdList="false" CombinedDecision="false"><Attributes Category="urn:oasis:names:tc:xacml:3.0:attribute-category:resource"><Attribute Issuer="issuer" IncludeInResult="false" AttributeId="urn:oasis:names:tc:xacml:1.0:resource:resource-id"><AttributeValue DataType="http://www.w3.org/2001/XMLSchema#string"/></Attribute></Attributes><Attributes Category="urn:oasis:names:tc:xacml:1.0:subject-category:access-subject"><Attribute Issuer="issuer" IncludeInResult="false" AttributeId="urn:oasis:names:tc:xacml:1.0:subject:subject-id"><AttributeValue DataType="http://www.w3.org/2001/XMLSchema#string">fedoraRole</AttributeValue></Attribute></Attributes><Attributes Category="urn:oasis:names:tc:xacml:3.0:attribute-category:action"><Attribute Issuer="issuer" IncludeInResult="false" AttributeId="urn:oasis:names:tc:xacml:1.0:action:action-id"><AttributeValue DataType="http://www.w3.org/2001/XMLSchema#string">urn:fedora:names:fedora:2.1:action:id-getDatastreamDissemination</AttributeValue></Attribute></Attributes></Request></ex:dom></value></param><param><value>https://localhost:8091</value></param><param><value><ex:nil/></value></param></params></methodCall>
<methodResponse xmlns:ex="http://ws.apache.org/xmlrpc/namespaces/extensions"><params><param><value><ex:dom><Response xmlns="urn:oasis:names:tc:xacml:3.0:core:schema:wd-17"><Result><Decision>Permit</Decision><StatusMessage/></Result><Session uuid="4E972183-E5C9-487F-89FF-FAAB12CA4A4F" uconUrl="https://localhost:8090" stateType="PASSIVE" stateName="TRY" ms="120"/></Response></ex:dom></value></param></params></methodResponse>
</record>
<record ms="6504">
<methodCall xmlns:ex="http://ws.apache.org/xmlrpc/namespaces/extensions"><methodName>UConS.assignCustomId</methodName><params><param><value>1987A4B8-97AA-4F03-AE21-87F6F40632A7</value></param><param><value><ex:nil/></value></param><param><value>ziopinetto-recycle</value></param></params></methodCall>
<methodResponse xmlns:ex="http://ws.apache.org/xmlrpc/namespaces/extensions"><params><param><value><ex:dom><Response xmlns="urn:oasis:names:tc:xacml:3.0:core:schema:wd-17"><Result><Decision>Permit</Decision><StatusMessage/></Result><Session uuid="1987A4B8-97AA-4F03-AE21-87F6F40632A7" uconUrl="https://localhost:8090" stateType="PASSIVE" stateName="TRY" customId="ziopinetto-recycle"/></Response></ex:dom></value></param></params></methodResponse>
</record>
<record ms="6534">
<methodCall xmlns:ex="http://ws.apache.org/xmlrpc/namespaces/extensions"><methodName>UConS.assignCustomId</methodName><params><param><value>4E972183-E5C9-487F-89FF-FAAB12CA4A4F</value></param><param><value><ex:nil/></value></param><param><value>ziopinetto-recycle</value></param></params></methodCall>
<methodResponse xmlns:ex="http://ws.apache.org/xmlrpc/namespaces/extensions"><fault><value><struct><member><name>faultCode</name><value><i4>0</i4></value></member><member><name>faultString</name><value>Failed to invoke method assignCustomId in class it.cnr.iit.retrail.server.impl.UConProtocolProxy: customId ziopinetto-recycle already exists</value></member></struct></value></fault></methodResponse>
</record>
<record ms="6545">
<methodCall xmlns:ex="http://ws.apache.org/xmlrpc/namespaces/extensions"><methodName>UConS.endAccess</methodName><params><param><value>1987A4B8-97AA-4F03-AE21-87F6F40632A7</value></param><param><value>ziopinetto-recycle</value></param></params></methodCall>
<methodResponse xmlns:ex="http://ws.apache.org/xmlrpc/namespaces/extensions"><params><param><value><ex:dom><Response xmlns="urn:oasis:names:tc:xacml:3.0:core:schema:wd-17"><Result><Decision>Permit</Decision><StatusMessage/></Result><Session uuid="1987A4B8-97AA-4F03-AE21-87F6F40632A7" uconUrl="https://localhost:8090" stateType="END" stateName="DELETED" ms="139" customId="ziopinetto-recycle"/></Response></ex:dom></value></param></params></methodResponse>
</record>
<record ms="6708">
<methodCall xmlns:ex="http://ws.apache.org/xmlrpc/namespaces/extensions"><methodName>UConS.endAccess</methodName><params><param><value>4E972183-E5C9-487F-89FF-FAAB12CA4A4F</value></param><param><value></value></param></params></methodCall>
<methodResponse xmlns:ex="http://ws.apache.org/xmlrpc/namespaces/extensions"><params><param><value><ex:dom><Response xmlns="urn:oasis:names:tc:xacml:3.0:core:schema:wd-17"><Result><Decision>Permit</Decision><StatusMessage/></Result><Session uuid="4E972183-E5C9-487F-89FF-FAAB12CA4A4F" uconUrl="https://localhost:8090" stateType="END" stateName="DELETED" ms="147"/></Response></ex:dom></value></param></params></methodResponse>
</record>
</retrailRecorder>